database_filtering/run_filtering.py
database_filtering/utils/utils.py
database_filtering-1.1.1.dist-info/METADATA
database_filtering-1.1.1.dist-info/WHEEL
database_filtering-1.1.1.dist-info/top_level.txt
database_filtering-1.1.1.dist-info/RECORD
