Metadata-Version: 2.1
Name: database-filtering
Version: 1.1.1
Summary: Filter database with r_group specification.
Home-page: https://github.com/hemahecodes/database_filtering
Download-URL: https://github.com/hemahecodes/database_filtering/archive/refs/tags/0.1.zip
Author: Helena Martín
Author-email: helena.martin@nostrumbiodiscovery.com
License: MIT
Keywords: filtering,database,rdkit
Classifier: Development Status :: 4 - Beta
Classifier: Intended Audience :: Developers
Classifier: Topic :: Software Development :: Build Tools
Classifier: License :: OSI Approved :: MIT License
Classifier: Programming Language :: Python :: 3
Classifier: Programming Language :: Python :: 3.4
Classifier: Programming Language :: Python :: 3.5
Classifier: Programming Language :: Python :: 3.6
Requires-Dist: validators
Requires-Dist: beautifulsoup4
Requires-Dist: argparse
Requires-Dist: pandas
Requires-Dist: networkx
